core/__init__.py
core/decoder.py
core/encoder.py
core/hasher.py
core/input_validator.py
core/rsa_crypto.py
core/unhasher.py
core/utils.py
cybercrypt-1.0.0.dist-info/LICENSE
cybercrypt-1.0.0.dist-info/METADATA
cybercrypt-1.0.0.dist-info/WHEEL
cybercrypt-1.0.0.dist-info/entry_points.txt
cybercrypt-1.0.0.dist-info/top_level.txt
cybercrypt-1.0.0.dist-info/RECORD
